funcnodes_numpy/__init__.py
funcnodes_numpy/_array_creation.py
funcnodes_numpy/_dtypes.py
funcnodes_numpy/_exportation.py
funcnodes_numpy/_ndarray.py
funcnodes_numpy/_types.py
funcnodes_numpy/_version.py
funcnodes_numpy/constants.py
funcnodes_numpy/_core/__init__.py
funcnodes_numpy/_core/_datetime.py
funcnodes_numpy/_core/_defchararray.py
funcnodes_numpy/_core/_fromnumeric.py
funcnodes_numpy/_core/_multiarray.py
funcnodes_numpy/_core/ufuncs.py
funcnodes_numpy/_lib/__init__.py
funcnodes_numpy/_lib/scimath.py
funcnodes_numpy/_linalg/__init__.py
funcnodes_numpy/_linalg/_linalg.py
funcnodes_numpy-0.2.11.dist-info/licenses/LICENSE
funcnodes_numpy-0.2.11.dist-info/METADATA
funcnodes_numpy-0.2.11.dist-info/WHEEL
funcnodes_numpy-0.2.11.dist-info/entry_points.txt
funcnodes_numpy-0.2.11.dist-info/top_level.txt
funcnodes_numpy-0.2.11.dist-info/RECORD
