Metadata-Version: 2.4
Name: funcnodes-numpy
Version: 0.2.11
Summary: implementations of numpy for funcnodes
Author-email: Julian Kimmig <julian.kimmig@gmx.net>
License: AGPL-3.0
Project-URL: homepage, https://github.com/Linkdlab/funcnodes_numpy
Project-URL: source, https://github.com/Linkdlab/funcnodes_numpy
Project-URL: tracker, https://github.com/Linkdlab/funcnodes_numpy/issues
Project-URL: download, https://pypi.org/project/funcnodes-numpy/#files
Classifier: License :: OSI Approved :: GNU Affero General Public License v3 or later (AGPLv3+)
Requires-Python: >=3.11
License-File: LICENSE
Requires-Dist: funcnodes
Requires-Dist: numpy
Dynamic: license-file
